kalliopepbx/Auth.py
kalliopepbx/Session.py
kalliopepbx/__init__.py
kalliopepbx/utils.py
kalliopepbx-0.0.3.dist-info/LICENSE
kalliopepbx-0.0.3.dist-info/METADATA
kalliopepbx-0.0.3.dist-info/WHEEL
kalliopepbx-0.0.3.dist-info/top_level.txt
kalliopepbx-0.0.3.dist-info/RECORD
